zqlib/__init__.py
zqlib/functions.py
zqlib/timer.py
zqlib-0.1.10.dist-info/LICENSE.txt
zqlib-0.1.10.dist-info/METADATA
zqlib-0.1.10.dist-info/WHEEL
zqlib-0.1.10.dist-info/top_level.txt
zqlib-0.1.10.dist-info/RECORD
