Metadata-Version: 2.1
Name: zqlib
Version: 0.1.10
Summary: Common used package of Qiang Zhou
Home-page: https://github.com/BillMills/python-package-example
Author: Qiang Zhou
Author-email: theodoruszq@gmail.com
License: MIT
Platform: UNKNOWN
Requires-Dist: numpy
Requires-Dist: opencv-python
